freshroastsr700_phidget/PhidgetHelperFunctions.py
freshroastsr700_phidget/__init__.py
freshroastsr700_phidget/max31865.py
freshroastsr700_phidget/test_phidget.py
freshroastsr700_phidget-1.2.dist-info/METADATA
freshroastsr700_phidget-1.2.dist-info/WHEEL
freshroastsr700_phidget-1.2.dist-info/top_level.txt
freshroastsr700_phidget-1.2.dist-info/RECORD
