Metadata-Version: 2.1
Name: freshroastsr700-phidget
Version: 1.2
Summary: An extended Python module to control a FreshRoastSR700 coffee roaster using a Phidget Temperature Sensor
Home-page: https://github.com/lucapinello/freshroastsr700_phidget
Author: Luca Pinello
Author-email: UNKNOWN
License: MIT
Platform: UNKNOWN
Requires-Dist: pyserial (>=3.0.1)
Requires-Dist: Phidget22
Requires-Dist: freshroastsr700 (>=0.2.1)
